{
    "Razor": "3", 
    "Naga Siren": "2", 
    "Goblin Techies": "1", 
    "Undying": "2", 
    "Dragon Knight": "1", 
    "Juggernaut": "2", 
    "Ursa": "2", 
    "Bane": "2", 
    "Pugna": "2", 
    "Tinker": "2", 
    "Ancient Apparition": "1", 
    "Omniknight": "1", 
    "Chaos Knight": "1", 
    "Outworld Devourer": "3", 
    "Abaddon": "1", 
    "Faceless Void": "3", 
    "Mirana": "2", 
    "Bristleback": "2", 
    "Elder Titan": "2", 
    "Slardar": "2", 
    "Shadow Fiend": "3", 
    "Templar Assassin": "2", 
    "Shadow Demon": "2", 
    "Keeper of the Light": "2", 
    "Necrophos": "2", 
    "Nightstalker": "1", 
    "Medusa": "1", 
    "Lone Druid": "1", 
    "Phantom Lancer": "2", 
    "Tiny": "1", 
    "Riki": "2", 
    "Invoker": "2", 
    "Sniper": "2", 
    "Meepo": "2", 
    "Leshrac": "1", 
    "Zeus": "3", 
    "Centaur": "1", 
    "Silencer": "2", 
    "Jakiro": "2", 
    "Broodmother": "1", 
    "Enigma": "2", 
    "Doom": "2", 
    "Lina": "3", 
    "Alchemist": "2", 
    "Batrider": "1", 
    "Brewmaster": "1", 
    "Axe": "3", 
    "Skywrath Mage": "1", 
    "Lifestealer": "3", 
    "Venomancer": "3", 
    "Morphling": "1", 
    "Death Prophet": "3", 
    "Lion": "2", 
    "Ogre Magi": "3", 
    "Dazzle": "1", 
    "Magnus": "1", 
    "Earth Spirit": "1", 
    "Pudge": "1", 
    "Storm Spirit": "2", 
    "Nature's Prophet": "1", 
    "Warlock": "3", 
    "Spirit Breaker": "2", 
    "Crystal Maiden": "3", 
    "Sven": "2", 
    "Huskar": "3", 
    "Shadow Shaman": "3", 
    "Treant Protector": "2", 
    "Sand King": "3", 
    "Dark Seer": "2", 
    "Clinkz": "2", 
    "Clockwerk": "2", 
    "Witch Doctor": "2", 
    "Enchantress": "2", 
    "Earthshaker": "2", 
    "Puck": "3", 
    "Nyx Assassin": "2", 
    "Bounty Hunter": "2", 
    "Luna": "2", 
    "Disruptor": "2", 
    "Timbersaw": "2", 
    "Queen of Pain": "2", 
    "Viper": "3", 
    "Tusk": "1", 
    "Lycan": "2", 
    "Phoenix": "1", 
    "Beastmaster": "1", 
    "Bloodseeker": "2", 
    "Gyrocopter": "2", 
    "Windranger": "3", 
    "Drow Ranger": "3", 
    "Vengeful Spirit": "3", 
    "Antimage": "3", 
    "Io": "1", 
    "Terrorblade": "3", 
    "Spectre": "3", 
    "Kunkka": "1", 
    "Slark": "2", 
    "Weaver": "3", 
    "Troll Warlord": "2", 
    "Lich": "3", 
    "Visage": "2", 
    "Ember Spirit": "2", 
    "Legion Commander": "1", 
    "Wraith King": "2", 
    "Tidehunter": "2", 
    "Phantom Assassin": "3", 
    "Chen": "1", 
    "Rubick": "1"
}